zhixin/__init__.py
zhixin/__main__.py
zhixin/app.py
zhixin/cache.py
zhixin/cli.py
zhixin/compat.py
zhixin/dependencies.py
zhixin/exception.py
zhixin/fs.py
zhixin/http.py
zhixin/maintenance.py
zhixin/proc.py
zhixin/public.py
zhixin/telemetry.py
zhixin/util.py
zhixin/account/__init__.py
zhixin/account/cli.py
zhixin/account/client.py
zhixin/account/validate.py
zhixin/account/commands/__init__.py
zhixin/account/commands/destroy.py
zhixin/account/commands/forgot.py
zhixin/account/commands/login.py
zhixin/account/commands/logout.py
zhixin/account/commands/password.py
zhixin/account/commands/register.py
zhixin/account/commands/show.py
zhixin/account/commands/token.py
zhixin/account/commands/update.py
zhixin/account/org/__init__.py
zhixin/account/org/cli.py
zhixin/account/org/commands/__init__.py
zhixin/account/org/commands/add.py
zhixin/account/org/commands/create.py
zhixin/account/org/commands/destroy.py
zhixin/account/org/commands/list.py
zhixin/account/org/commands/remove.py
zhixin/account/org/commands/update.py
zhixin/account/team/__init__.py
zhixin/account/team/cli.py
zhixin/account/team/commands/__init__.py
zhixin/account/team/commands/add.py
zhixin/account/team/commands/create.py
zhixin/account/team/commands/destroy.py
zhixin/account/team/commands/list.py
zhixin/account/team/commands/remove.py
zhixin/account/team/commands/update.py
zhixin/builder/__init__.py
zhixin/builder/main.py
zhixin/builder/tools/__init__.py
zhixin/builder/tools/zxasm.py
zhixin/builder/tools/zxbuild.py
zhixin/builder/tools/zxhooks.py
zhixin/builder/tools/zxino.py
zhixin/builder/tools/zxintegration.py
zhixin/builder/tools/zxlib.py
zhixin/builder/tools/zxmaxlen.py
zhixin/builder/tools/zxmisc.py
zhixin/builder/tools/zxplatform.py
zhixin/builder/tools/zxproject.py
zhixin/builder/tools/zxsize.py
zhixin/builder/tools/zxtarget.py
zhixin/builder/tools/zxtest.py
zhixin/builder/tools/zxupload.py
zhixin/check/__init__.py
zhixin/check/cli.py
zhixin/check/defect.py
zhixin/check/tools/__init__.py
zhixin-3.3.63.dist-info/LICENSE
zhixin-3.3.63.dist-info/METADATA
zhixin-3.3.63.dist-info/WHEEL
zhixin-3.3.63.dist-info/entry_points.txt
zhixin-3.3.63.dist-info/top_level.txt
zhixin-3.3.63.dist-info/RECORD
