Metadata-Version: 2.1
Name: zhixin
Version: 3.3.63
Home-page: https://ZhiXin-Semi.com
Author: ZhiXin-Semi
Author-email: contact@ZhiXin-Semi.com
Keywords: embedded,arm,ide,microcontroller,debug
Classifier: Development Status :: 5 - Production/Stable
Classifier: Environment :: Console
Classifier: Intended Audience :: Developers
Classifier: License :: OSI Approved :: Apache Software License
Classifier: Operating System :: OS Independent
Classifier: Programming Language :: C
Classifier: Programming Language :: Python
Classifier: Programming Language :: Python :: 3
Classifier: Topic :: Software Development
Classifier: Topic :: Software Development :: Build Tools
Classifier: Topic :: Software Development :: Compilers
Requires-Python: >=3.6
License-File: LICENSE
Requires-Dist: bottle==0.13.*
Requires-Dist: click<9,>=8.0.4
Requires-Dist: colorama
Requires-Dist: marshmallow==3.*
Requires-Dist: pyelftools<1,>=0.27
Requires-Dist: pyserial==3.5.*
Requires-Dist: requests==2.*
Requires-Dist: semantic-version==2.10.*
Requires-Dist: tabulate==0.*
Requires-Dist: ajsonrpc==1.2.*
Requires-Dist: starlette<0.38,>=0.19
Requires-Dist: uvicorn<0.30,>=0.16
Requires-Dist: wsproto==1.*
